odoo9_addon_purchase_order_type-9.0.1.1.0-py2.7-nspkg.pth
odoo_addons/purchase_order_type/__openerp__.py
odoo_addons/purchase_order_type/__init__.py
odoo_addons/purchase_order_type/README.rst
odoo_addons/purchase_order_type/security/ir.model.access.csv
odoo_addons/purchase_order_type/models/res_partner.py
odoo_addons/purchase_order_type/models/purchase_order.py
odoo_addons/purchase_order_type/models/purchase_order_type.py
odoo_addons/purchase_order_type/models/__init__.py
odoo_addons/purchase_order_type/i18n/ja.po
odoo_addons/purchase_order_type/i18n/lv.po
odoo_addons/purchase_order_type/i18n/zh_CN.po
odoo_addons/purchase_order_type/i18n/nb_NO.po
odoo_addons/purchase_order_type/i18n/uk.po
odoo_addons/purchase_order_type/i18n/es_AR.po
odoo_addons/purchase_order_type/i18n/ko.po
odoo_addons/purchase_order_type/i18n/ru.po
odoo_addons/purchase_order_type/i18n/gl_ES.po
odoo_addons/purchase_order_type/i18n/pt.po
odoo_addons/purchase_order_type/i18n/fr_CH.po
odoo_addons/purchase_order_type/i18n/it.po
odoo_addons/purchase_order_type/i18n/es_CL.po
odoo_addons/purchase_order_type/i18n/es.po
odoo_addons/purchase_order_type/i18n/nl_BE.po
odoo_addons/purchase_order_type/i18n/fr_FR.po
odoo_addons/purchase_order_type/i18n/ar.po
odoo_addons/purchase_order_type/i18n/lt.po
odoo_addons/purchase_order_type/i18n/vi_VN.po
odoo_addons/purchase_order_type/i18n/ro.po
odoo_addons/purchase_order_type/i18n/tr.po
odoo_addons/purchase_order_type/i18n/sr.po
odoo_addons/purchase_order_type/i18n/es_PY.po
odoo_addons/purchase_order_type/i18n/mk.po
odoo_addons/purchase_order_type/i18n/hr.po
odoo_addons/purchase_order_type/i18n/bg.po
odoo_addons/purchase_order_type/i18n/es_EC.po
odoo_addons/purchase_order_type/i18n/zh_TW.po
odoo_addons/purchase_order_type/i18n/hu.po
odoo_addons/purchase_order_type/i18n/fr_CA.po
odoo_addons/purchase_order_type/i18n/gl.po
odoo_addons/purchase_order_type/i18n/lt_LT.po
odoo_addons/purchase_order_type/i18n/ca.po
odoo9_addon_purchase_order_type-9.0.1.1.0.dist-info/top_level.txt
odoo9_addon_purchase_order_type-9.0.1.1.0.dist-info/WHEEL
odoo9_addon_purchase_order_type-9.0.1.1.0.dist-info/RECORD
odoo9_addon_purchase_order_type-9.0.1.1.0.dist-info/metadata.json
odoo9_addon_purchase_order_type-9.0.1.1.0.dist-info/DESCRIPTION.rst
odoo9_addon_purchase_order_type-9.0.1.1.0.dist-info/METADATA
odoo9_addon_purchase_order_type-9.0.1.1.0.dist-info/namespace_packages.txt
